tag_uri/__init__.py
tag_uri/__main__.py
tag_uri/grammar.lark
tag_uri/py.typed
tag_uri/tag_uri.py
tag_uri-0.1.1.dist-info/LICENSE
tag_uri-0.1.1.dist-info/METADATA
tag_uri-0.1.1.dist-info/WHEEL
tag_uri-0.1.1.dist-info/entry_points.txt
tag_uri-0.1.1.dist-info/RECORD
