Metadata-Version: 2.1
Name: tag-uri
Version: 0.1.1
Summary: RFC 4151 Tag URI taguri.org parser and generator
Home-page: https://git.sr.ht/~cellofellow/tag_uri
License: MIT
Keywords: rfc4151,uri,parser,taguri.org
Author: Josh Gardner
Author-email: jdg@jgardner.tech
Requires-Python: >=3.11,<4.0
Classifier: License :: OSI Approved :: MIT License
Classifier: Programming Language :: Python :: 3
Classifier: Programming Language :: Python :: 3.11
Classifier: Programming Language :: Python :: 3.12
Classifier: Topic :: Internet
Classifier: Topic :: Software Development :: Libraries
Classifier: Typing :: Typed
Requires-Dist: lark (>=1.1.9,<2.0.0)
Project-URL: Repository, https://git.sr.ht/~cellofellow/tag_uri
